readmat.py
readmat-0.0.1.data/scripts/readmat.py
readmat-0.0.1.dist-info/LICENSE.txt
readmat-0.0.1.dist-info/METADATA
readmat-0.0.1.dist-info/WHEEL
readmat-0.0.1.dist-info/top_level.txt
readmat-0.0.1.dist-info/RECORD
