Metadata-Version: 2.1
Name: readmat
Version: 0.0.1
Summary: Helpful functions for loading .mat MATLAB files into Python. Most data types are supported.
Home-page: https://github.com/AnthonyAndroulakis/readmat
Author: Anthony Androulakis & stackoverflow users cs01, jpapon, and andyvanee
Author-email: aandroulakis@zoho.com
License: MIT
Download-URL: https://github.com/AnthonyAndroulakis/readmat/archive/v_001.tar.gz
Keywords: mat,matlab,python,utilities,tool,read,readmat,loadmat,load,struct,structure
Platform: UNKNOWN
Classifier: Development Status :: 5 - Production/Stable
Classifier: License :: OSI Approved :: MIT License
Classifier: Programming Language :: Python :: 3
Requires-Dist: scipy
Requires-Dist: numpy
